{
  "version": 3,
  "middleware": {
    "/": {
      "files": [
        "server/edge-runtime-webpack.js",
        "server/src/middleware.js"
      ],
      "entrypoint": "server/src/middleware.js",
      "name": "src/middleware",
      "page": "/",
      "matchers": [
        {
          "regexp": "^(?:\\/(_next\\/data\\/[^/]{1,}))?(?:\\/((?!api|_next|_vercel|.*\\..*).*))(\\.json)?[\\/#\\?]?$",
          "originalSource": "/((?!api|_next|_vercel|.*\\..*).*)"
        }
      ],
      "wasm": [],
      "assets": [],
      "env": {
        "__NEXT_BUILD_ID": "AAZWCbxOAz3WNzJHhbf9-",
        "NEXT_SERVER_ACTIONS_ENCRYPTION_KEY": "6jOMPGs9Rk+3AnlYx8HRYI9GSt3oScsqeRxxPSNTKiM=",
        "__NEXT_PREVIEW_MODE_ID": "81320c46d4cab0b3b9b0be0ee5ae301b",
        "__NEXT_PREVIEW_MODE_SIGNING_KEY": "1b75941f085b9de16ace878bf53a44450e49fff347952c5cc20b2f882e63996c",
        "__NEXT_PREVIEW_MODE_ENCRYPTION_KEY": "f3e8f90806b3b7f638834a0cc66cf5fdf8b9a6f5bb9817ef25e2134476ef33df"
      }
    }
  },
  "functions": {},
  "sortedMiddleware": [
    "/"
  ]
}